docs/config.md
docs/framework.md
docs/index.md
docs/pipeline.md
docs/quantification.md
docs/segmentation.md
docs/infer_subc/organelles.md
docs/infer_subc/overview.md
docs/infer_subc/workflow.md
docs/infer_subc/core/file_io.md
docs/infer_subc/core/img.md
docs/infer_subc/napari/organelle_config.md
docs/infer_subc/napari/plugin.md
docs/infer_subc/organelles/cellmask.md
docs/infer_subc/organelles/cytoplasm.md
docs/infer_subc/organelles/er.md
docs/infer_subc/organelles/golgi.md
docs/infer_subc/organelles/lipid.md
docs/infer_subc/organelles/lysosome.md
docs/infer_subc/organelles/mitochondria.md
docs/infer_subc/organelles/nuclei.md
docs/infer_subc/organelles/peroxisome.md
docs/infer_subc/utils/batch.md
docs/infer_subc/utils/etc.md
docs/infer_subc/utils/stats.md
docs/infer_subc/utils/stats_helpers.md
docs/infer_subc/utils/utils.md
docs/nbs/overview.md
infer_subc/__init__.py
infer_subc/__main__.py
infer_subc/_version.py
infer_subc/cli.py
infer_subc/constants.py
infer_subc/exceptions.py
infer_subc/assets/0.7.LD.html
infer_subc/assets/0.7.LD.md
infer_subc/assets/0.7.LD.txt
infer_subc/assets/README.png
infer_subc/assets/diagrams/0.7.LD.png
infer_subc/core/__init__.py
infer_subc/core/file_io.py
infer_subc/core/img.py
infer_subc/core/zslice.py
infer_subc/organelles/__init__.py
infer_subc/organelles/cellmask.py
infer_subc/organelles/cytoplasm.py
infer_subc/organelles/er.py
infer_subc/organelles/golgi.py
infer_subc/organelles/lipid.py
infer_subc/organelles/lysosome.py
infer_subc/organelles/masks.py
infer_subc/organelles/mitochondria.py
infer_subc/organelles/nuclei.py
infer_subc/organelles/peroxisome.py
infer_subc/organelles/qc.py
infer_subc/organelles_config/__init__.py
infer_subc/organelles_config/all_functions.json
infer_subc/organelles_config/conf_0.1.masks.json
infer_subc/organelles_config/conf_0.1.masks_A.json
infer_subc/organelles_config/conf_0.1.masks_B.json
infer_subc/organelles_config/conf_0.2.lyso.json
infer_subc/organelles_config/conf_0.3.mito.json
infer_subc-1.0.6.dist-info/licenses/LICENSE
infer_subc-1.0.6.dist-info/METADATA
infer_subc-1.0.6.dist-info/WHEEL
infer_subc-1.0.6.dist-info/top_level.txt
infer_subc-1.0.6.dist-info/RECORD
