Metadata-Version: 2.4
Name: infer-subc
Version: 1.0.6
Summary: A plugin that enables organelle segmentation and analysis
Author-email: Andy Henrie <ergonyc@gmail.com>, Shannon Rhoads <rhoads.shannon@gmail.com>, Rene Mfulama <mfulamangudiankama@gmail.com>, Zach coman <zachcoman@gmail.com>
Maintainer-email: Shannon Rhoads <rhoads.shannon@gmail.com>, Rene Mfulama <mfulamangudiankama@gmail.com>, Zach coman <zachcoman@gmail.com>
License: Copyright (c) 2022, Shannon Rhoads
Keywords: organelles,segmentation,morphology,organelle contacts,distribution,ER,lysosomes,mitochondria,peroxisomes,Golgi,lipid droplets
Classifier: Development Status :: 3 - Alpha
Classifier: Intended Audience :: Science/Research
Classifier: Topic :: Scientific/Engineering
Classifier: Topic :: Scientific/Engineering :: Visualization
Classifier: Topic :: Scientific/Engineering :: Information Analysis
Classifier: Topic :: Scientific/Engineering :: Bio-Informatics
Classifier: Programming Language :: Python
Classifier: Programming Language :: Python :: 3
Classifier: Programming Language :: Python :: 3.8
Classifier: Programming Language :: Python :: 3.9
Classifier: Programming Language :: Python :: 3.10
Classifier: Operating System :: OS Independent
Requires-Python: >=3.7
License-File: LICENSE
Requires-Dist: numpy<=1.26.4,>=1.15.1
Requires-Dist: napari
Requires-Dist: napari-aicsimageio
Requires-Dist: aicssegmentation
Requires-Dist: aicsimageio>=4.7.0
Requires-Dist: scipy
Requires-Dist: scikit-learn
Requires-Dist: pandas
Requires-Dist: centrosome
Requires-Dist: aicspylibczi>=3.1.1
Dynamic: license-file
